README.txt
setup.py
collective/__init__.py
collective.portlet.feedmixer.egg-info/PKG-INFO
collective.portlet.feedmixer.egg-info/SOURCES.txt
collective.portlet.feedmixer.egg-info/dependency_links.txt
collective.portlet.feedmixer.egg-info/namespace_packages.txt
collective.portlet.feedmixer.egg-info/not-zip-safe
collective.portlet.feedmixer.egg-info/requires.txt
collective.portlet.feedmixer.egg-info/top_level.txt
collective/portlet/__init__.py
collective/portlet/feedmixer/__init__.py
collective/portlet/feedmixer/configure.zcml
collective/portlet/feedmixer/full.pt
collective/portlet/feedmixer/full.py
collective/portlet/feedmixer/interfaces.py
collective/portlet/feedmixer/portlet.pt
collective/portlet/feedmixer/portlet.py
collective/portlet/feedmixer/version.txt
collective/portlet/feedmixer/vocabulary.py
collective/portlet/feedmixer/locales/collective.portlet.feedmixer.pot
collective/portlet/feedmixer/locales/da/LC_MESSAGES/collective.portlet.feedmixer.mo
collective/portlet/feedmixer/locales/da/LC_MESSAGES/collective.portlet.feedmixer.po
collective/portlet/feedmixer/locales/es/LC_MESSAGES/collective.portlet.feedmixer.mo
collective/portlet/feedmixer/locales/es/LC_MESSAGES/collective.portlet.feedmixer.po
collective/portlet/feedmixer/locales/fr/LC_MESSAGES/collective.portlet.feedmixer.mo
collective/portlet/feedmixer/locales/fr/LC_MESSAGES/collective.portlet.feedmixer.po
collective/portlet/feedmixer/locales/pt_BR/LC_MESSAGES/collective.portlet.feedmixer.mo
collective/portlet/feedmixer/locales/pt_BR/LC_MESSAGES/collective.portlet.feedmixer.po
collective/portlet/feedmixer/profiles/default/portlets.xml
collective/portlet/feedmixer/tests/__init__.py
collective/portlet/feedmixer/tests/base.py
collective/portlet/feedmixer/tests/feed1.xml
collective/portlet/feedmixer/tests/feed2.xml
collective/portlet/feedmixer/tests/test_feed.py
collective/portlet/feedmixer/tests/test_portlet.py
collective/portlet/feedmixer/tests/test_utils.py
docs/HISTORY.txt
docs/INSTALL.txt
docs/LICENSE.GPL
docs/LICENSE.txt