Metadata-Version: 1.0
Name: collective.portlet.feedmixer
Version: 1.6
Summary: Portlet which can show multiple feeds
Home-page: http://plone.org
Author: Wichert Akkerman - Jarn
Author-email: wichert@jarn.com
License: GPL
Keywords: plone rss atom feed portlet
Platform: UNKNOWN
Classifier: Framework :: Plone
Classifier: Framework :: Zope2
Classifier: Programming Language :: Python
Classifier: Topic :: Software Development :: Libraries :: Python Modules
